django_icon_picker/__init__.py
django_icon_picker/apps.py
django_icon_picker/field.py
django_icon_picker/urls.py
django_icon_picker/views.py
django_icon_picker/widgets.py
django_icon_picker/static/django_icon_picker/css/icon_picker.css
django_icon_picker/static/django_icon_picker/js/icon_picker.js
django_icon_picker/templates/django_icon_picker/icon_picker.html
django_icon_picker-1.0.2.dist-info/METADATA
django_icon_picker-1.0.2.dist-info/WHEEL
django_icon_picker-1.0.2.dist-info/top_level.txt
django_icon_picker-1.0.2.dist-info/RECORD
